autodeploy/__init__.py
autodeploy/deployer.py
watsonx_autodeploy-0.1.2.dist-info/licenses/LICENSE
watsonx_autodeploy-0.1.2.dist-info/METADATA
watsonx_autodeploy-0.1.2.dist-info/WHEEL
watsonx_autodeploy-0.1.2.dist-info/top_level.txt
watsonx_autodeploy-0.1.2.dist-info/RECORD
