Metadata-Version: 2.4
Name: watsonx-autodeploy
Version: 0.1.2
Summary: Automated deployment library for IBM WatsonX AI services with LangGraph support
Author-email: Nicholas Renotte <nick@nichollasrenotte.com>
License-Expression: MIT
Project-URL: Homepage, https://github.com/nicknochnack/watsonx-autodeploy
Project-URL: Repository, https://github.com/nicknochnack/watsonx-autodeploy.git
Project-URL: Issues, https://github.com/nicknochnack/watsonx-autodeploy/issues
Keywords: watsonx,ai,deployment,langgraph,automation
Classifier: Development Status :: 3 - Alpha
Classifier: Intended Audience :: Developers
Classifier: Programming Language :: Python :: 3
Classifier: Programming Language :: Python :: 3.11
Classifier: Programming Language :: Python :: 3.12
Classifier: Topic :: Software Development :: Libraries :: Python Modules
Classifier: Topic :: Scientific/Engineering :: Artificial Intelligence
Requires-Python: >=3.11
License-File: LICENSE
Requires-Dist: ibm-watsonx-ai>=1.3.34
Requires-Dist: python-dotenv>=1.1.1
Provides-Extra: dev
Requires-Dist: build>=1.3.0; extra == "dev"
Requires-Dist: twine>=6.1.0; extra == "dev"
Requires-Dist: pytest>=7.0; extra == "dev"
Requires-Dist: black>=23.0; extra == "dev"
Requires-Dist: flake8>=6.0; extra == "dev"
Requires-Dist: mypy>=1.0; extra == "dev"
Dynamic: license-file
